fastbarnes/__init__.py
fastbarnes/interpolation.py
fastbarnes/interpolationS2.py
fastbarnes/util/__init__.py
fastbarnes/util/kdtree.py
fastbarnes/util/lambert_conformal.py
fast_barnes_py-2.0.0.dist-info/METADATA
fast_barnes_py-2.0.0.dist-info/WHEEL
fast_barnes_py-2.0.0.dist-info/top_level.txt
fast_barnes_py-2.0.0.dist-info/RECORD
