Metadata-Version: 2.1
Name: fast-barnes-py
Version: 2.0.0
Summary: Fast Barnes Interpolation
Home-page: https://github.com/MeteoSwiss/fast-barnes-py/
Author: Bruno Zürcher
Author-email: bruno.zuercher@meteoswiss.ch
License: BSD 3-Clause License
Keywords: python,interpolation,gridding,inverse distance weighting,fast algorithms,Gaussian,convolution
Classifier: Development Status :: 4 - Beta
Classifier: Intended Audience :: Developers
Classifier: Intended Audience :: Science/Research
Classifier: License :: OSI Approved :: BSD License
Classifier: Operating System :: OS Independent
Classifier: Programming Language :: Python :: 3.9
Classifier: Programming Language :: Python :: 3.10
Classifier: Programming Language :: Python :: 3.11
Classifier: Programming Language :: Python :: 3.12
Classifier: Topic :: Scientific/Engineering
Classifier: Topic :: Scientific/Engineering :: Atmospheric Science
Classifier: Topic :: Scientific/Engineering :: GIS
Classifier: Topic :: Scientific/Engineering :: Mathematics
Classifier: Topic :: Scientific/Engineering :: Oceanography
Requires-Python: >=3.9, <3.13
Requires-Dist: numpy
Requires-Dist: scipy
Requires-Dist: numba
